pianohat.py
pianohat-0.1.0.dist-info/metadata.json
pianohat-0.1.0.dist-info/WHEEL
pianohat-0.1.0.dist-info/METADATA
pianohat-0.1.0.dist-info/DESCRIPTION.rst
pianohat-0.1.0.dist-info/top_level.txt
pianohat-0.1.0.dist-info/RECORD
